almapiwrapper/__init__.py
almapiwrapper/apikeys.py
almapiwrapper/configlog.py
almapiwrapper/record.py
almapiwrapper/version.py
almapiwrapper/acquisitions/__init__.py
almapiwrapper/acquisitions/invoice.py
almapiwrapper/acquisitions/poline.py
almapiwrapper/acquisitions/vendor.py
almapiwrapper/analytics/__init__.py
almapiwrapper/analytics/report.py
almapiwrapper/config/__init__.py
almapiwrapper/config/job.py
almapiwrapper/config/library.py
almapiwrapper/config/recset.py
almapiwrapper/config/reminder.py
almapiwrapper/inventory/__init__.py
almapiwrapper/inventory/bib.py
almapiwrapper/inventory/collection.py
almapiwrapper/inventory/holding.py
almapiwrapper/inventory/item.py
almapiwrapper/users/__init__.py
almapiwrapper/users/fee.py
almapiwrapper/users/loan.py
almapiwrapper/users/request.py
almapiwrapper/users/user.py
almapiwrapper/users/utils.py
almapiwrapper-1.4.0.dist-info/licenses/licence.txt
test/__init__.py
test/test_analytics.py
test/test_bib.py
test/test_config.py
test/test_fee.py
test/test_fetchusers.py
test/test_invoice.py
test/test_loan.py
test/test_pol.py
test/test_recset.py
test/test_request.py
test/test_user.py
test/test_vendor.py
almapiwrapper-1.4.0.dist-info/METADATA
almapiwrapper-1.4.0.dist-info/WHEEL
almapiwrapper-1.4.0.dist-info/top_level.txt
almapiwrapper-1.4.0.dist-info/RECORD
