Metadata-Version: 2.4
Name: almapiwrapper
Version: 1.4.0
Summary: This python module is a tool to use Alma APIs. it manages the logs and the backup of the records.
Author-email: Raphaël Rey <raphael.rey@slsp.ch>
License-Expression: GPL-3.0-or-later
Project-URL: Homepage, https://github.com/Swiss-Library-Service-Platform/almapiwrapper
Project-URL: Bug Tracker, https://github.com/Swiss-Library-Service-Platform/almapiwrapper/issues
Classifier: Programming Language :: Python :: 3
Classifier: Operating System :: OS Independent
Requires-Python: >=3.9
License-File: licence.txt
Dynamic: license-file
